LICENSE
MANIFEST.in
requirements.txt
setup.py
version.py
docs/README.rst
ucuenca/__init__.py
ucuenca/ucuenca.py
ucuenca.egg-info/PKG-INFO
ucuenca.egg-info/SOURCES.txt
ucuenca.egg-info/dependency_links.txt
ucuenca.egg-info/requires.txt
ucuenca.egg-info/top_level.txt