Metadata-Version: 1.1
Name: ucuenca
Version: 0.1.3.0
Summary: Librería de Python para la API de la Universidad de Cuenca
Home-page: https://github.com/stsewd/ucuenca.py
Author: Santos Gallegos
Author-email: santos_g@outlook.com
License: MIT
Keywords: ucuenca api development
Platform: UNKNOWN
Classifier: Programming Language :: Python :: 3
Classifier: Programming Language :: Python :: 3.3
Classifier: Programming Language :: Python :: 3.4
Classifier: Programming Language :: Python :: 3.5
